<annotation>
	<folder>train</folder>
	<filename>p433.jpg</filename>
	<path>C:\Users\Pc\tensorflow\PPE\train\p433.jpg</path>
	<source>
		<database>Unknown</database>
	</source>
	<size>
		<width>400</width>
		<height>297</height>
		<depth>3</depth>
	</size>
	<segmented>0</segmented>
	<object>
		<name>epi</name>
		<pose>Unspecified</pose>
		<truncated>1</truncated>
		<difficult>0</difficult>
		<bndbox>
			<xmin>228</xmin>
			<ymin>2</ymin>
			<xmax>400</xmax>
			<ymax>297</ymax>
		</bndbox>
	</object>
</annotation>
